{
  "as_of": "2026-05-22",
  "data_source": "yfinance",
  "market_regime": "bull_lo",
  "posterior": 0.9250815249677236,
  "hmm_diagnostics": {
    "n_refit": 58,
    "n_below_z_thresh": 58,
    "median_z_separation": 0.8617378927200601
  },
  "drift_p_up_latest": 0.5422568737547013,
  "curve_beta_latest": 0.0004577156682996861,
  "recommendation": {
    "structure": "bull_call_debit_spread",
    "legs": [
      {
        "cp": "call",
        "delta": 0.55,
        "pos": 1
      },
      {
        "cp": "call",
        "delta": 0.3,
        "pos": -1
      }
    ]
  },
  "per_name": {
    "AAPL": {
      "as_of": "2026-05-22",
      "cell": "bull_lo",
      "rs_z_short": 1.224352460455177,
      "rs_z_long": 0.5423829646556892,
      "recommendation": {
        "structure": "bull_call_debit_spread",
        "legs": [
          {
            "cp": "call",
            "delta": 0.55,
            "pos": 1
          },
          {
            "cp": "call",
            "delta": 0.3,
            "pos": -1
          }
        ]
      }
    },
    "MSFT": {
      "as_of": "2026-05-22",
      "cell": "neut_hi",
      "rs_z_short": -0.3413401959818987,
      "rs_z_long": 0.3964470903496534,
      "recommendation": {
        "structure": "wide_bull_put_credit_spread",
        "legs": [
          {
            "cp": "put",
            "delta": -0.2,
            "pos": -1
          },
          {
            "cp": "put",
            "delta": -0.1,
            "pos": 1
          }
        ]
      }
    },
    "NVDA": {
      "as_of": "2026-05-22",
      "cell": "neut_hi",
      "rs_z_short": -0.04066076513812188,
      "rs_z_long": -0.4259099061611573,
      "recommendation": {
        "structure": "wide_bull_put_credit_spread",
        "legs": [
          {
            "cp": "put",
            "delta": -0.2,
            "pos": -1
          },
          {
            "cp": "put",
            "delta": -0.1,
            "pos": 1
          }
        ]
      }
    },
    "AMZN": {
      "as_of": "2026-05-22",
      "cell": "bull_lo",
      "rs_z_short": -0.17953511265964453,
      "rs_z_long": 2.316483416511096,
      "recommendation": {
        "structure": "bull_call_debit_spread",
        "legs": [
          {
            "cp": "call",
            "delta": 0.55,
            "pos": 1
          },
          {
            "cp": "call",
            "delta": 0.3,
            "pos": -1
          }
        ]
      }
    },
    "GOOGL": {
      "as_of": "2026-05-22",
      "cell": "neut_hi",
      "rs_z_short": 0.2858387894023278,
      "rs_z_long": -0.07513294733655476,
      "recommendation": {
        "structure": "wide_bull_put_credit_spread",
        "legs": [
          {
            "cp": "put",
            "delta": -0.2,
            "pos": -1
          },
          {
            "cp": "put",
            "delta": -0.1,
            "pos": 1
          }
        ]
      }
    },
    "META": {
      "as_of": "2026-05-22",
      "cell": "neut_lo",
      "rs_z_short": -1.4690749419956264,
      "rs_z_long": -0.7694870107809397,
      "recommendation": {
        "structure": "no_trade",
        "legs": []
      }
    },
    "JPM": {
      "as_of": "2026-05-22",
      "cell": "neut_hi",
      "rs_z_short": -1.605121152322399,
      "rs_z_long": -1.2354051083632922,
      "recommendation": {
        "structure": "wide_bull_put_credit_spread",
        "legs": [
          {
            "cp": "put",
            "delta": -0.2,
            "pos": -1
          },
          {
            "cp": "put",
            "delta": -0.1,
            "pos": 1
          }
        ]
      }
    },
    "BAC": {
      "as_of": "2026-05-22",
      "cell": "neut_lo",
      "rs_z_short": -1.2618561539661546,
      "rs_z_long": -1.2819471802872455,
      "recommendation": {
        "structure": "no_trade",
        "legs": []
      }
    },
    "XOM": {
      "as_of": "2026-05-22",
      "cell": "neut_hi",
      "rs_z_short": -0.3072030478325632,
      "rs_z_long": -0.6856649899577075,
      "recommendation": {
        "structure": "wide_bull_put_credit_spread",
        "legs": [
          {
            "cp": "put",
            "delta": -0.2,
            "pos": -1
          },
          {
            "cp": "put",
            "delta": -0.1,
            "pos": 1
          }
        ]
      }
    },
    "CVX": {
      "as_of": "2026-05-22",
      "cell": "neut_hi",
      "rs_z_short": -0.3752467380832041,
      "rs_z_long": -0.5053986628845655,
      "recommendation": {
        "structure": "wide_bull_put_credit_spread",
        "legs": [
          {
            "cp": "put",
            "delta": -0.2,
            "pos": -1
          },
          {
            "cp": "put",
            "delta": -0.1,
            "pos": 1
          }
        ]
      }
    },
    "UNH": {
      "as_of": "2026-05-22",
      "cell": "bull_lo",
      "rs_z_short": 0.4005872601639991,
      "rs_z_long": 1.3343342474322453,
      "recommendation": {
        "structure": "bull_call_debit_spread",
        "legs": [
          {
            "cp": "call",
            "delta": 0.55,
            "pos": 1
          },
          {
            "cp": "call",
            "delta": 0.3,
            "pos": -1
          }
        ]
      }
    },
    "JNJ": {
      "as_of": "2026-05-22",
      "cell": "neut_hi",
      "rs_z_short": -0.6827411214198068,
      "rs_z_long": -1.6612017816787417,
      "recommendation": {
        "structure": "wide_bull_put_credit_spread",
        "legs": [
          {
            "cp": "put",
            "delta": -0.2,
            "pos": -1
          },
          {
            "cp": "put",
            "delta": -0.1,
            "pos": 1
          }
        ]
      }
    },
    "V": {
      "as_of": "2026-05-22",
      "cell": "bull_hi",
      "rs_z_short": 1.141319380051399,
      "rs_z_long": 1.2174381961690455,
      "recommendation": {
        "structure": "short_put",
        "legs": [
          {
            "cp": "put",
            "delta": -0.3,
            "pos": -1
          }
        ]
      }
    },
    "MA": {
      "as_of": "2026-05-22",
      "cell": "neut_hi",
      "rs_z_short": -0.6690653508212453,
      "rs_z_long": -0.2703321944096831,
      "recommendation": {
        "structure": "wide_bull_put_credit_spread",
        "legs": [
          {
            "cp": "put",
            "delta": -0.2,
            "pos": -1
          },
          {
            "cp": "put",
            "delta": -0.1,
            "pos": 1
          }
        ]
      }
    },
    "PG": {
      "as_of": "2026-05-22",
      "cell": "neut_hi",
      "rs_z_short": -0.44901661571964274,
      "rs_z_long": -1.6043544850661844,
      "recommendation": {
        "structure": "wide_bull_put_credit_spread",
        "legs": [
          {
            "cp": "put",
            "delta": -0.2,
            "pos": -1
          },
          {
            "cp": "put",
            "delta": -0.1,
            "pos": 1
          }
        ]
      }
    },
    "KO": {
      "as_of": "2026-05-22",
      "cell": "neut_hi",
      "rs_z_short": 0.4638233051276459,
      "rs_z_long": -0.4931979021496677,
      "recommendation": {
        "structure": "wide_bull_put_credit_spread",
        "legs": [
          {
            "cp": "put",
            "delta": -0.2,
            "pos": -1
          },
          {
            "cp": "put",
            "delta": -0.1,
            "pos": 1
          }
        ]
      }
    },
    "HD": {
      "as_of": "2026-05-22",
      "cell": "neut_hi",
      "rs_z_short": -1.580321229598005,
      "rs_z_long": -2.0973721890643833,
      "recommendation": {
        "structure": "wide_bull_put_credit_spread",
        "legs": [
          {
            "cp": "put",
            "delta": -0.2,
            "pos": -1
          },
          {
            "cp": "put",
            "delta": -0.1,
            "pos": 1
          }
        ]
      }
    },
    "DIS": {
      "as_of": "2026-05-22",
      "cell": "neut_hi",
      "rs_z_short": -0.739453808928968,
      "rs_z_long": -0.6234865880334409,
      "recommendation": {
        "structure": "wide_bull_put_credit_spread",
        "legs": [
          {
            "cp": "put",
            "delta": -0.2,
            "pos": -1
          },
          {
            "cp": "put",
            "delta": -0.1,
            "pos": 1
          }
        ]
      }
    },
    "CSCO": {
      "as_of": "2026-05-22",
      "cell": "bull_hi",
      "rs_z_short": 3.7506643942001547,
      "rs_z_long": 3.9079178870757576,
      "recommendation": {
        "structure": "short_put",
        "legs": [
          {
            "cp": "put",
            "delta": -0.3,
            "pos": -1
          }
        ]
      }
    },
    "WMT": {
      "as_of": "2026-05-22",
      "cell": "neut_hi",
      "rs_z_short": -2.709510270920018,
      "rs_z_long": -1.7732112350036655,
      "recommendation": {
        "structure": "wide_bull_put_credit_spread",
        "legs": [
          {
            "cp": "put",
            "delta": -0.2,
            "pos": -1
          },
          {
            "cp": "put",
            "delta": -0.1,
            "pos": 1
          }
        ]
      }
    },
    "WFC": {
      "as_of": "2026-05-22",
      "cell": "neut_lo",
      "rs_z_short": -1.3229914115320827,
      "rs_z_long": -1.9502927958687584,
      "recommendation": {
        "structure": "no_trade",
        "legs": []
      }
    },
    "GS": {
      "as_of": "2026-05-22",
      "cell": "neut_hi",
      "rs_z_short": -0.08552887262106734,
      "rs_z_long": -0.5447451646041941,
      "recommendation": {
        "structure": "wide_bull_put_credit_spread",
        "legs": [
          {
            "cp": "put",
            "delta": -0.2,
            "pos": -1
          },
          {
            "cp": "put",
            "delta": -0.1,
            "pos": 1
          }
        ]
      }
    },
    "MS": {
      "as_of": "2026-05-22",
      "cell": "neut_lo",
      "rs_z_short": -0.005932930486709657,
      "rs_z_long": 0.9334553325793253,
      "recommendation": {
        "structure": "no_trade",
        "legs": []
      }
    },
    "C": {
      "as_of": "2026-05-22",
      "cell": "neut_lo",
      "rs_z_short": -1.6544495412849878,
      "rs_z_long": -0.6834660305253866,
      "recommendation": {
        "structure": "no_trade",
        "legs": []
      }
    },
    "SCHW": {
      "as_of": "2026-05-22",
      "cell": "neut_hi",
      "rs_z_short": -0.36053588733849146,
      "rs_z_long": -1.3783679503475954,
      "recommendation": {
        "structure": "wide_bull_put_credit_spread",
        "legs": [
          {
            "cp": "put",
            "delta": -0.2,
            "pos": -1
          },
          {
            "cp": "put",
            "delta": -0.1,
            "pos": 1
          }
        ]
      }
    },
    "LLY": {
      "as_of": "2026-05-22",
      "cell": "neut_hi",
      "rs_z_short": 1.0081673544104084,
      "rs_z_long": -0.3777101923454089,
      "recommendation": {
        "structure": "wide_bull_put_credit_spread",
        "legs": [
          {
            "cp": "put",
            "delta": -0.2,
            "pos": -1
          },
          {
            "cp": "put",
            "delta": -0.1,
            "pos": 1
          }
        ]
      }
    },
    "ABBV": {
      "as_of": "2026-05-22",
      "cell": "neut_lo",
      "rs_z_short": 0.5390946653052637,
      "rs_z_long": -1.3048413658446312,
      "recommendation": {
        "structure": "no_trade",
        "legs": []
      }
    },
    "MRK": {
      "as_of": "2026-05-22",
      "cell": "neut_hi",
      "rs_z_short": 0.052517791087680024,
      "rs_z_long": -0.8447682146961617,
      "recommendation": {
        "structure": "wide_bull_put_credit_spread",
        "legs": [
          {
            "cp": "put",
            "delta": -0.2,
            "pos": -1
          },
          {
            "cp": "put",
            "delta": -0.1,
            "pos": 1
          }
        ]
      }
    },
    "PFE": {
      "as_of": "2026-05-22",
      "cell": "neut_lo",
      "rs_z_short": -0.9757991401063727,
      "rs_z_long": -1.374088737954956,
      "recommendation": {
        "structure": "no_trade",
        "legs": []
      }
    },
    "TMO": {
      "as_of": "2026-05-22",
      "cell": "neut_lo",
      "rs_z_short": -0.843197324507235,
      "rs_z_long": -1.11910983194329,
      "recommendation": {
        "structure": "no_trade",
        "legs": []
      }
    },
    "CAT": {
      "as_of": "2026-05-22",
      "cell": "neut_hi",
      "rs_z_short": -0.9837401846186207,
      "rs_z_long": -1.327403256806407,
      "recommendation": {
        "structure": "wide_bull_put_credit_spread",
        "legs": [
          {
            "cp": "put",
            "delta": -0.2,
            "pos": -1
          },
          {
            "cp": "put",
            "delta": -0.1,
            "pos": 1
          }
        ]
      }
    },
    "HON": {
      "as_of": "2026-05-22",
      "cell": "neut_hi",
      "rs_z_short": 0.4136963949287182,
      "rs_z_long": -1.0085071514722577,
      "recommendation": {
        "structure": "wide_bull_put_credit_spread",
        "legs": [
          {
            "cp": "put",
            "delta": -0.2,
            "pos": -1
          },
          {
            "cp": "put",
            "delta": -0.1,
            "pos": 1
          }
        ]
      }
    },
    "RTX": {
      "as_of": "2026-05-22",
      "cell": "neut_lo",
      "rs_z_short": -0.8897684112919597,
      "rs_z_long": -2.8942435856293427,
      "recommendation": {
        "structure": "no_trade",
        "legs": []
      }
    },
    "BA": {
      "as_of": "2026-05-22",
      "cell": "neut_hi",
      "rs_z_short": -1.3608069976449135,
      "rs_z_long": -1.063854643795793,
      "recommendation": {
        "structure": "wide_bull_put_credit_spread",
        "legs": [
          {
            "cp": "put",
            "delta": -0.2,
            "pos": -1
          },
          {
            "cp": "put",
            "delta": -0.1,
            "pos": 1
          }
        ]
      }
    },
    "NKE": {
      "as_of": "2026-05-22",
      "cell": "neut_lo",
      "rs_z_short": -0.08407774531738764,
      "rs_z_long": -1.791948186482432,
      "recommendation": {
        "structure": "no_trade",
        "legs": []
      }
    },
    "MCD": {
      "as_of": "2026-05-22",
      "cell": "neut_hi",
      "rs_z_short": -1.4413598972512711,
      "rs_z_long": -2.3112468464130327,
      "recommendation": {
        "structure": "wide_bull_put_credit_spread",
        "legs": [
          {
            "cp": "put",
            "delta": -0.2,
            "pos": -1
          },
          {
            "cp": "put",
            "delta": -0.1,
            "pos": 1
          }
        ]
      }
    },
    "SBUX": {
      "as_of": "2026-05-22",
      "cell": "neut_hi",
      "rs_z_short": -0.15821802709939667,
      "rs_z_long": 0.2497455996254826,
      "recommendation": {
        "structure": "wide_bull_put_credit_spread",
        "legs": [
          {
            "cp": "put",
            "delta": -0.2,
            "pos": -1
          },
          {
            "cp": "put",
            "delta": -0.1,
            "pos": 1
          }
        ]
      }
    },
    "LOW": {
      "as_of": "2026-05-22",
      "cell": "neut_hi",
      "rs_z_short": -2.0808999658636527,
      "rs_z_long": -2.4855266650001164,
      "recommendation": {
        "structure": "wide_bull_put_credit_spread",
        "legs": [
          {
            "cp": "put",
            "delta": -0.2,
            "pos": -1
          },
          {
            "cp": "put",
            "delta": -0.1,
            "pos": 1
          }
        ]
      }
    },
    "TGT": {
      "as_of": "2026-05-22",
      "cell": "neut_hi",
      "rs_z_short": -1.0983723808971708,
      "rs_z_long": 0.1341182795619312,
      "recommendation": {
        "structure": "wide_bull_put_credit_spread",
        "legs": [
          {
            "cp": "put",
            "delta": -0.2,
            "pos": -1
          },
          {
            "cp": "put",
            "delta": -0.1,
            "pos": 1
          }
        ]
      }
    },
    "PEP": {
      "as_of": "2026-05-22",
      "cell": "neut_hi",
      "rs_z_short": -1.1566774558299038,
      "rs_z_long": -1.6003773951174405,
      "recommendation": {
        "structure": "wide_bull_put_credit_spread",
        "legs": [
          {
            "cp": "put",
            "delta": -0.2,
            "pos": -1
          },
          {
            "cp": "put",
            "delta": -0.1,
            "pos": 1
          }
        ]
      }
    },
    "COST": {
      "as_of": "2026-05-22",
      "cell": "neut_hi",
      "rs_z_short": -0.28773620885348866,
      "rs_z_long": -0.01261427402274443,
      "recommendation": {
        "structure": "wide_bull_put_credit_spread",
        "legs": [
          {
            "cp": "put",
            "delta": -0.2,
            "pos": -1
          },
          {
            "cp": "put",
            "delta": -0.1,
            "pos": 1
          }
        ]
      }
    },
    "ADBE": {
      "as_of": "2026-05-22",
      "cell": "bull_hi",
      "rs_z_short": 0.4402982774768719,
      "rs_z_long": 0.8514031776721431,
      "recommendation": {
        "structure": "short_put",
        "legs": [
          {
            "cp": "put",
            "delta": -0.3,
            "pos": -1
          }
        ]
      }
    },
    "CRM": {
      "as_of": "2026-05-22",
      "cell": "bull_hi",
      "rs_z_short": 0.5080857615737966,
      "rs_z_long": 0.7425822424904205,
      "recommendation": {
        "structure": "short_put",
        "legs": [
          {
            "cp": "put",
            "delta": -0.3,
            "pos": -1
          }
        ]
      }
    },
    "AVGO": {
      "as_of": "2026-05-22",
      "cell": "neut_lo",
      "rs_z_short": -1.2652081277500176,
      "rs_z_long": 0.19719153418884533,
      "recommendation": {
        "structure": "no_trade",
        "legs": []
      }
    },
    "QCOM": {
      "as_of": "2026-05-22",
      "cell": "bull_hi",
      "rs_z_short": 4.45297140799201,
      "rs_z_long": 3.561708146145371,
      "recommendation": {
        "structure": "short_put",
        "legs": [
          {
            "cp": "put",
            "delta": -0.3,
            "pos": -1
          }
        ]
      }
    },
    "NFLX": {
      "as_of": "2026-05-22",
      "cell": "neut_lo",
      "rs_z_short": -0.5333068745158123,
      "rs_z_long": 0.7640218865878748,
      "recommendation": {
        "structure": "no_trade",
        "legs": []
      }
    },
    "AMD": {
      "as_of": "2026-05-22",
      "cell": "bull_hi",
      "rs_z_short": 1.5203742585712081,
      "rs_z_long": 2.875423969154259,
      "recommendation": {
        "structure": "short_put",
        "legs": [
          {
            "cp": "put",
            "delta": -0.3,
            "pos": -1
          }
        ]
      }
    },
    "COP": {
      "as_of": "2026-05-22",
      "cell": "neut_hi",
      "rs_z_short": -0.9082672142789304,
      "rs_z_long": -0.07310995450502462,
      "recommendation": {
        "structure": "wide_bull_put_credit_spread",
        "legs": [
          {
            "cp": "put",
            "delta": -0.2,
            "pos": -1
          },
          {
            "cp": "put",
            "delta": -0.1,
            "pos": 1
          }
        ]
      }
    },
    "VZ": {
      "as_of": "2026-05-22",
      "cell": "neut_lo",
      "rs_z_short": -0.21416425618480509,
      "rs_z_long": -0.6668947130053015,
      "recommendation": {
        "structure": "no_trade",
        "legs": []
      }
    },
    "LIN": {
      "as_of": "2026-05-22",
      "cell": "neut_hi",
      "rs_z_short": -0.35959954287369245,
      "rs_z_long": -0.17324841288811094,
      "recommendation": {
        "structure": "wide_bull_put_credit_spread",
        "legs": [
          {
            "cp": "put",
            "delta": -0.2,
            "pos": -1
          },
          {
            "cp": "put",
            "delta": -0.1,
            "pos": 1
          }
        ]
      }
    }
  },
  "iv_snapshot_coverage": "50/50"
}